authly/__init__.py
authly/__main__.py
authly/_version.py
authly/app.py
authly/embedded.py
authly/main.py
authly/admin/__init__.py
authly/admin/api_client.py
authly/admin/auth_commands.py
authly/admin/cache.py
authly/admin/cli.py
authly/admin/client_commands.py
authly/admin/error_handler.py
authly/admin/errors.py
authly/admin/models.py
authly/admin/permissions.py
authly/admin/request_middleware.py
authly/admin/scope_commands.py
authly/admin/validation.py
authly/api/__init__.py
authly/api/admin_dependencies.py
authly/api/admin_middleware.py
authly/api/admin_router.py
authly/api/auth_dependencies.py
authly/api/auth_router.py
authly/api/health_router.py
authly/api/metrics_router.py
authly/api/oauth_discovery_router.py
authly/api/oauth_router.py
authly/api/oidc_router.py
authly/api/password_change.py
authly/api/rate_limiter.py
authly/api/security_middleware.py
authly/api/users_dependencies.py
authly/api/users_router.py
authly/api/validation_models.py
authly/auth/__init__.py
authly/auth/core.py
authly/bootstrap/__init__.py
authly/bootstrap/admin_seeding.py
authly/config/__init__.py
authly/config/config.py
authly/config/database_providers.py
authly/config/secret_providers.py
authly/config/secure.py
authly/core/__init__.py
authly/core/backend_factory.py
authly/core/backends.py
authly/core/database.py
authly/core/dependencies.py
authly/core/deployment_modes.py
authly/core/mode_factory.py
authly/core/resource_manager.py
authly/logging/__init__.py
authly/logging/context.py
authly/logging/formatter.py
authly/logging/helpers.py
authly/logging/middleware.py
authly/logging/setup.py
authly/monitoring/metrics.py
authly/monitoring/middleware.py
authly/oauth/__init__.py
authly/oauth/authorization_code_repository.py
authly/oauth/authorization_service.py
authly/oauth/client_repository.py
authly/oauth/client_service.py
authly/oauth/discovery_models.py
authly/oauth/discovery_service.py
authly/oauth/models.py
authly/oauth/scope_repository.py
authly/oauth/scope_service.py
authly-0.5.7.dist-info/METADATA
authly-0.5.7.dist-info/WHEEL
authly-0.5.7.dist-info/entry_points.txt
authly-0.5.7.dist-info/licenses/LICENSE
authly-0.5.7.dist-info/RECORD
