Metadata-Version: 2.4
Name: authly
Version: 0.5.7
Summary: Authorization & User Token Handling Layer for You
Project-URL: Homepage, https://github.com/descoped/authly
Project-URL: Repository, https://github.com/descoped/authly
Project-URL: Issues, https://github.com/descoped/authly/issues
Author-email: Ove Ranheim <oranheim@gmail.com>
License-File: LICENSE
Keywords: asyncio,authentication,authorization,fastapi,iam,identity,oauth,oauth2,oidc,security
Classifier: License :: OSI Approved :: MIT License
Classifier: Operating System :: OS Independent
Classifier: Programming Language :: Python :: 3
Classifier: Programming Language :: Python :: 3.11
Requires-Python: >=3.11
Requires-Dist: bcrypt==4.3.0
Requires-Dist: click>=8.1.7
Requires-Dist: coverage>=7.9.2
Requires-Dist: cryptography>=44.0.1
Requires-Dist: fastapi>=0.116.1
Requires-Dist: httpx>=0.28.1
Requires-Dist: jinja2>=3.1.6
Requires-Dist: prometheus-client>=0.20.0
Requires-Dist: psycopg-pool>=3.2.4
Requires-Dist: psycopg-toolkit>=0.2.0
Requires-Dist: psycopg[binary]>=3.2.3
Requires-Dist: pydantic-settings>=2.1.0
Requires-Dist: pydantic>=2.10.5
Requires-Dist: pyjwt>=2.10.1
Requires-Dist: python-dotenv>=1.0.1
Requires-Dist: python-jose[cryptography]>=3.3.0
Requires-Dist: python-multipart>=0.0.6
Requires-Dist: starlette>=0.47.2
Requires-Dist: tenacity>=9.0.0
Requires-Dist: tomli>=2.2.1
Requires-Dist: uvicorn>=0.35.0
